ipwg/__init__.py
ipwg/entry.py
ipwg/generator.py
ipwg/util.py
ipwg-0.1.0.dist-info/METADATA
ipwg-0.1.0.dist-info/WHEEL
ipwg-0.1.0.dist-info/entry_points.txt
ipwg-0.1.0.dist-info/top_level.txt
ipwg-0.1.0.dist-info/RECORD
