Metadata-Version: 2.1
Name: ipwg
Version: 0.1.0
Summary: Password Generator
Home-page: https://github.com/en0/ipwg
Author: Ian Laird
Author-email: irlaird@gmail.com
License: MIT
Keywords: password
Platform: UNKNOWN
Classifier: Programming Language :: Python :: 3
Classifier: License :: OSI Approved :: MIT License
Classifier: Operating System :: OS Independent
